AUTHORS.rst
CONTRIBUTING.rst
HISTORY.rst
LICENSE
MANIFEST.in
README.rst
setup.cfg
setup.py
docs/Makefile
docs/authors.rst
docs/conf.py
docs/contributing.rst
docs/history.rst
docs/index.rst
docs/installation.rst
docs/make.bat
docs/readme.rst
docs/usage.rst
here_geocoding/__init__.py
here_geocoding/cli.py
here_geocoding/here_geocoding.py
here_geocoding.egg-info/PKG-INFO
here_geocoding.egg-info/SOURCES.txt
here_geocoding.egg-info/dependency_links.txt
here_geocoding.egg-info/entry_points.txt
here_geocoding.egg-info/not-zip-safe
here_geocoding.egg-info/requires.txt
here_geocoding.egg-info/top_level.txt
tests/__init__.py
tests/address-sample.xlsx
tests/examples.py
tests/test_here_geocoding.py