Metadata-Version: 2.1
Name: here-geocoding
Version: 0.3.0
Summary: The "here-geocoding" package is a Python library designed to streamline the process of converting addresses stored in an Excel (xlsx) file into latitude and longitude coordinates. It provides a convenient solution for geocoding large sets of addresses using the HERE geocoding service.
Home-page: https://github.com/Mariosmsk/here_geocoding
Author: Marios S. Kyriakou
Author-email: mariosmsk@gmail.com
License: MIT license
Keywords: here_geocoding
Classifier: Development Status :: 2 - Pre-Alpha
Classifier: Intended Audience :: Developers
Classifier: License :: OSI Approved :: MIT License
Classifier: Natural Language :: English
Classifier: Programming Language :: Python :: 3
Classifier: Programming Language :: Python :: 3.6
Classifier: Programming Language :: Python :: 3.7
Classifier: Programming Language :: Python :: 3.8
Classifier: Programming Language :: Python :: 3.9
Classifier: Programming Language :: Python :: 3.10
Requires-Python: >=3.6
License-File: LICENSE
License-File: AUTHORS.rst
